{
  "id": "keys-splines-indicative-01",
  "moduleId": "keys-splines",
  "designCode": "INDICATIVE",
  "description": "Parallel key — 50 mm shaft, 800 N·m torque",
  "inputs": {
    "shaftDiameter": 0.05,
    "keyWidth": 0.014,
    "keyHeight": 0.009,
    "keyLength": 0.04,
    "torque": 800,
    "yieldStress": 250000000
  },
  "expected": {
    "shearSafety": 2.625,
    "bearingSafety": 2.109375
  },
  "tolerancePercent": 5,
  "source": "Shigley-style parallel key: τ=T/(0.5·d·w·L), σ_b=2T/(d·(h/2)·L); τ_all=0.6 Sy, σ_all=1.5 Sy"
}
